LICENSE
MANIFEST.in
README.rst
setup.py
django_modelmultivalue.egg-info/PKG-INFO
django_modelmultivalue.egg-info/SOURCES.txt
django_modelmultivalue.egg-info/dependency_links.txt
django_modelmultivalue.egg-info/requires.txt
django_modelmultivalue.egg-info/top_level.txt
modelmultivalue/__init__.py
modelmultivalue/fields.py
modelmultivalue/widgets.py
tests/__init__.py
tests/conftest.py
tests/settings.py
tests/test_choice_and_multi.py
tests/test_form.py
tests/test_form_meta.py
tests/test_app/__init__.py
tests/test_app/forms.py
tests/test_app/models.py